<?xml version="1.0" encoding="UTF-8"?>
<!--                                                                      -->
<!-- Generated by Semifore, Inc. csrCompile                               -->
<!--   Version: 2009.01                                                   -->
<!--   Released on: Mar 25 2009 12:03:56                                  -->
<!--   Spirit IP-XACT 1.4 output                                          -->
<!--                                                                      -->
<!-- Input files:                                                         -->
<!--    generic_example.rdl                                               -->
<!--                                                                      -->
<!-- Generated on: Wed Mar 25 12:43:22 2009                               -->
<!--           by: weber                                                  -->
<!--                                                                      -->
<!--
// Revision:    $Revision:$
// Date:        $Date:$
//
// Copyright (c) 2009 The SPIRIT Consortium.
//
// This work forms part of a deliverable of The SPIRIT Consortium.
//
// Use of these materials are governed by the legal terms and conditions
// outlined in the disclaimer available from www.spiritconsortium.org.
//
// This source file is provided on an AS IS basis.  The SPIRIT
// Consortium disclaims any warranty express or implied including
// any warranty of merchantability and fitness for use for a
// particular purpose.
//
// The user of the source file shall indemnify and hold The SPIRIT
// Consortium and its members harmless from any damages or liability.
// Users are requested to provide feedback to The SPIRIT Consortium
// using either mailto:feedback@lists.spiritconsortium.org or the forms at
// http://www.spiritconsortium.org/about/contact_us/
//
// This file may be copied, and distributed, with or without
// modifications; this notice must be included on any copy.
-->
<spirit:component xmlns:kactus2="http://funbase.cs.tut.fi/" xmlns:spirit="http://www.spiritconsortium.org/XMLSchema/SPIRIT/1.5" xmlns:xsi="http://www.w3.org/2001/XMLSchema-instance" xsi:schemaLocation="http://www.spiritconsortium.org/XMLSchema/SPIRIT/1.5 http://www.spiritconsortium.org/XMLSchema/SPIRIT/1.5/index.xsd">
	<spirit:vendor>org.example</spirit:vendor>
	<spirit:library>example_lib</spirit:library>
	<spirit:name>example_name</spirit:name>
	<spirit:version>example_version</spirit:version>
	<spirit:memoryMaps>
 <spirit:memoryMap>
  <spirit:name>some_register_map</spirit:name>
  <spirit:displayName>RDL Example Registers</spirit:displayName>
  <spirit:addressBlock>
   <spirit:name>some_register_map</spirit:name>
   <spirit:displayName>RDL Example Registers</spirit:displayName>
   <spirit:description>This address map contains some example registers to show how RDL can be utilized in various situations.</spirit:description>
   <spirit:baseAddress>0x0</spirit:baseAddress>
   <spirit:range>0x2000</spirit:range>
   <spirit:width>32</spirit:width>
   <spirit:usage>register</spirit:usage>
   <spirit:volatile>true</spirit:volatile>
   <spirit:register>
    <spirit:name>chip_id_reg</spirit:name>
    <spirit:displayName>This chip part number and revision #</spirit:displayName>
    <spirit:description>This register cotains the part # and revision # for XYZ ASIC</spirit:description>
    <spirit:addressOffset>0x0</spirit:addressOffset>
    <spirit:size>32</spirit:size>
    <spirit:volatile>true</spirit:volatile>
    <spirit:access>read-write</spirit:access>
    <spirit:reset>
     <spirit:value>0x12345671</spirit:value>
     <spirit:mask>0xffffffff</spirit:mask>
    </spirit:reset>
    <spirit:field>
     <spirit:name>rev_num</spirit:name>
     <spirit:description>This field represents the chips revision number</spirit:description>
     <spirit:bitOffset>0</spirit:bitOffset>
     <spirit:bitWidth>4</spirit:bitWidth>
     <spirit:access>read-only</spirit:access>
    </spirit:field>
    <spirit:field>
     <spirit:name>part_num</spirit:name>
     <spirit:description>This field represents the chips part number</spirit:description>
     <spirit:bitOffset>4</spirit:bitOffset>
     <spirit:bitWidth>28</spirit:bitWidth>
     <spirit:access>read-only</spirit:access>
    </spirit:field>
   </spirit:register>
   <spirit:register>
    <spirit:name>link_status</spirit:name>
    <spirit:addressOffset>0x4</spirit:addressOffset>
    <spirit:size>32</spirit:size>
    <spirit:volatile>true</spirit:volatile>
    <spirit:access>read-write</spirit:access>
    <spirit:reset>
     <spirit:value>0x0</spirit:value>
     <spirit:mask>0xffff0000</spirit:mask>
    </spirit:reset>
    <spirit:field>
     <spirit:name>port0</spirit:name>
     <spirit:description>Status of a Serdes Link</spirit:description>
     <spirit:bitOffset>0</spirit:bitOffset>
     <spirit:bitWidth>4</spirit:bitWidth>
     <spirit:access>read-only</spirit:access>
     <spirit:values>
      <spirit:value>0x0</spirit:value>
      <spirit:name>not_present</spirit:name>
     </spirit:values>
     <spirit:values>
      <spirit:value>0x1</spirit:value>
      <spirit:name>training</spirit:name>
     </spirit:values>
     <spirit:values>
      <spirit:value>0x5</spirit:value>
      <spirit:name>snooze</spirit:name>
     </spirit:values>
     <spirit:values>
      <spirit:value>0x6</spirit:value>
      <spirit:name>sleep</spirit:name>
     </spirit:values>
     <spirit:values>
      <spirit:value>0x7</spirit:value>
      <spirit:name>wake</spirit:name>
     </spirit:values>
     <spirit:values>
      <spirit:value>0xa</spirit:value>
      <spirit:name>active</spirit:name>
     </spirit:values>
    </spirit:field>
    <spirit:field>
     <spirit:name>port1</spirit:name>
     <spirit:description>Status of a Serdes Link</spirit:description>
     <spirit:bitOffset>4</spirit:bitOffset>
     <spirit:bitWidth>4</spirit:bitWidth>
     <spirit:access>read-only</spirit:access>
     <spirit:values>
      <spirit:value>0x0</spirit:value>
      <spirit:name>not_present</spirit:name>
     </spirit:values>
     <spirit:values>
      <spirit:value>0x1</spirit:value>
      <spirit:name>training</spirit:name>
     </spirit:values>
     <spirit:values>
      <spirit:value>0x5</spirit:value>
      <spirit:name>snooze</spirit:name>
     </spirit:values>
     <spirit:values>
      <spirit:value>0x6</spirit:value>
      <spirit:name>sleep</spirit:name>
     </spirit:values>
     <spirit:values>
      <spirit:value>0x7</spirit:value>
      <spirit:name>wake</spirit:name>
     </spirit:values>
     <spirit:values>
      <spirit:value>0xa</spirit:value>
      <spirit:name>active</spirit:name>
     </spirit:values>
    </spirit:field>
    <spirit:field>
     <spirit:name>port2</spirit:name>
     <spirit:description>Status of a Serdes Link</spirit:description>
     <spirit:bitOffset>8</spirit:bitOffset>
     <spirit:bitWidth>4</spirit:bitWidth>
     <spirit:access>read-only</spirit:access>
     <spirit:values>
      <spirit:value>0x0</spirit:value>
      <spirit:name>not_present</spirit:name>
     </spirit:values>
     <spirit:values>
      <spirit:value>0x1</spirit:value>
      <spirit:name>training</spirit:name>
     </spirit:values>
     <spirit:values>
      <spirit:value>0x5</spirit:value>
      <spirit:name>snooze</spirit:name>
     </spirit:values>
     <spirit:values>
      <spirit:value>0x6</spirit:value>
      <spirit:name>sleep</spirit:name>
     </spirit:values>
     <spirit:values>
      <spirit:value>0x7</spirit:value>
      <spirit:name>wake</spirit:name>
     </spirit:values>
     <spirit:values>
      <spirit:value>0xa</spirit:value>
      <spirit:name>active</spirit:name>
     </spirit:values>
    </spirit:field>
    <spirit:field>
     <spirit:name>port3</spirit:name>
     <spirit:description>Status of a Serdes Link</spirit:description>
     <spirit:bitOffset>12</spirit:bitOffset>
     <spirit:bitWidth>4</spirit:bitWidth>
     <spirit:access>read-only</spirit:access>
     <spirit:values>
      <spirit:value>0x0</spirit:value>
      <spirit:name>not_present</spirit:name>
     </spirit:values>
     <spirit:values>
      <spirit:value>0x1</spirit:value>
      <spirit:name>training</spirit:name>
     </spirit:values>
     <spirit:values>
      <spirit:value>0x5</spirit:value>
      <spirit:name>snooze</spirit:name>
     </spirit:values>
     <spirit:values>
      <spirit:value>0x6</spirit:value>
      <spirit:name>sleep</spirit:name>
     </spirit:values>
     <spirit:values>
      <spirit:value>0x7</spirit:value>
      <spirit:name>wake</spirit:name>
     </spirit:values>
     <spirit:values>
      <spirit:value>0xa</spirit:value>
      <spirit:name>active</spirit:name>
     </spirit:values>
    </spirit:field>
   </spirit:register>
   <spirit:register>
    <spirit:name>myRegInst</spirit:name>
    <spirit:addressOffset>0x10</spirit:addressOffset>
    <spirit:size>32</spirit:size>
    <spirit:volatile>true</spirit:volatile>
    <spirit:access>read-write</spirit:access>
    <spirit:reset>
     <spirit:value>0xe4e4e4e4</spirit:value>
     <spirit:mask>0xffffffff</spirit:mask>
    </spirit:reset>
    <spirit:field>
     <spirit:name>data0</spirit:name>
     <spirit:description>My example 2bit status field</spirit:description>
     <spirit:bitOffset>0</spirit:bitOffset>
     <spirit:bitWidth>2</spirit:bitWidth>
     <spirit:access>read-write</spirit:access>
    </spirit:field>
    <spirit:field>
     <spirit:name>data1</spirit:name>
     <spirit:description>My example 2bit status field</spirit:description>
     <spirit:bitOffset>2</spirit:bitOffset>
     <spirit:bitWidth>2</spirit:bitWidth>
     <spirit:access>read-write</spirit:access>
    </spirit:field>
    <spirit:field>
     <spirit:name>data2</spirit:name>
     <spirit:description>My example 2bit status field</spirit:description>
     <spirit:bitOffset>4</spirit:bitOffset>
     <spirit:bitWidth>2</spirit:bitWidth>
     <spirit:access>read-write</spirit:access>
    </spirit:field>
    <spirit:field>
     <spirit:name>data3</spirit:name>
     <spirit:description>My example 2bit status field</spirit:description>
     <spirit:bitOffset>6</spirit:bitOffset>
     <spirit:bitWidth>2</spirit:bitWidth>
     <spirit:access>read-write</spirit:access>
    </spirit:field>
    <spirit:field>
     <spirit:name>data4</spirit:name>
     <spirit:description>My example 2bit status field</spirit:description>
     <spirit:bitOffset>8</spirit:bitOffset>
     <spirit:bitWidth>2</spirit:bitWidth>
     <spirit:access>read-write</spirit:access>
    </spirit:field>
    <spirit:field>
     <spirit:name>data5</spirit:name>
     <spirit:description>My example 2bit status field</spirit:description>
     <spirit:bitOffset>10</spirit:bitOffset>
     <spirit:bitWidth>2</spirit:bitWidth>
     <spirit:access>read-write</spirit:access>
    </spirit:field>
    <spirit:field>
     <spirit:name>data6</spirit:name>
     <spirit:description>My example 2bit status field</spirit:description>
     <spirit:bitOffset>12</spirit:bitOffset>
     <spirit:bitWidth>2</spirit:bitWidth>
     <spirit:access>read-write</spirit:access>
    </spirit:field>
    <spirit:field>
     <spirit:name>data7</spirit:name>
     <spirit:description>My example 2bit status field</spirit:description>
     <spirit:bitOffset>14</spirit:bitOffset>
     <spirit:bitWidth>2</spirit:bitWidth>
     <spirit:access>read-write</spirit:access>
    </spirit:field>
    <spirit:field>
     <spirit:name>data8</spirit:name>
     <spirit:description>My example 2bit status field</spirit:description>
     <spirit:bitOffset>16</spirit:bitOffset>
     <spirit:bitWidth>2</spirit:bitWidth>
     <spirit:access>read-write</spirit:access>
    </spirit:field>
    <spirit:field>
     <spirit:name>data9</spirit:name>
     <spirit:description>My example 2bit status field</spirit:description>
     <spirit:bitOffset>18</spirit:bitOffset>
     <spirit:bitWidth>2</spirit:bitWidth>
     <spirit:access>read-write</spirit:access>
    </spirit:field>
    <spirit:field>
     <spirit:name>data10</spirit:name>
     <spirit:description>My example 2bit status field</spirit:description>
     <spirit:bitOffset>20</spirit:bitOffset>
     <spirit:bitWidth>2</spirit:bitWidth>
     <spirit:access>read-write</spirit:access>
    </spirit:field>
    <spirit:field>
     <spirit:name>data11</spirit:name>
     <spirit:description>My example 2bit status field</spirit:description>
     <spirit:bitOffset>22</spirit:bitOffset>
     <spirit:bitWidth>2</spirit:bitWidth>
     <spirit:access>read-write</spirit:access>
    </spirit:field>
    <spirit:field>
     <spirit:name>data12</spirit:name>
     <spirit:description>My example 2bit status field</spirit:description>
     <spirit:bitOffset>24</spirit:bitOffset>
     <spirit:bitWidth>2</spirit:bitWidth>
     <spirit:access>read-write</spirit:access>
    </spirit:field>
    <spirit:field>
     <spirit:name>data13</spirit:name>
     <spirit:description>My example 2bit status field</spirit:description>
     <spirit:bitOffset>26</spirit:bitOffset>
     <spirit:bitWidth>2</spirit:bitWidth>
     <spirit:access>read-write</spirit:access>
    </spirit:field>
    <spirit:field>
     <spirit:name>data14</spirit:name>
     <spirit:description>My example 2bit status field</spirit:description>
     <spirit:bitOffset>28</spirit:bitOffset>
     <spirit:bitWidth>2</spirit:bitWidth>
     <spirit:access>read-write</spirit:access>
    </spirit:field>
    <spirit:field>
     <spirit:name>data15</spirit:name>
     <spirit:description>My example 2bit status field</spirit:description>
     <spirit:bitOffset>30</spirit:bitOffset>
     <spirit:bitWidth>2</spirit:bitWidth>
     <spirit:access>read-write</spirit:access>
    </spirit:field>
   </spirit:register>
   <spirit:register>
    <spirit:name>spi4_pkt_count</spirit:name>
    <spirit:addressOffset>0x20</spirit:addressOffset>
    <spirit:size>32</spirit:size>
    <spirit:volatile>true</spirit:volatile>
    <spirit:access>read-write</spirit:access>
    <spirit:field>
     <spirit:name>port1</spirit:name>
     <spirit:description>Number of certain packet type seen</spirit:description>
     <spirit:bitOffset>0</spirit:bitOffset>
     <spirit:bitWidth>16</spirit:bitWidth>
     <spirit:access>read-write</spirit:access>
    </spirit:field>
    <spirit:field>
     <spirit:name>port0</spirit:name>
     <spirit:description>Number of certain packet type seen</spirit:description>
     <spirit:bitOffset>16</spirit:bitOffset>
     <spirit:bitWidth>16</spirit:bitWidth>
     <spirit:access>read-write</spirit:access>
    </spirit:field>
   </spirit:register>
   <spirit:register>
    <spirit:name>gige_pkt_count_reg</spirit:name>
    <spirit:addressOffset>0x24</spirit:addressOffset>
    <spirit:size>32</spirit:size>
    <spirit:volatile>true</spirit:volatile>
    <spirit:access>read-write</spirit:access>
    <spirit:field>
     <spirit:name>port3</spirit:name>
     <spirit:description>Number of certain packet type seen</spirit:description>
     <spirit:bitOffset>0</spirit:bitOffset>
     <spirit:bitWidth>8</spirit:bitWidth>
     <spirit:access>read-write</spirit:access>
    </spirit:field>
    <spirit:field>
     <spirit:name>port2</spirit:name>
     <spirit:description>Number of certain packet type seen</spirit:description>
     <spirit:bitOffset>8</spirit:bitOffset>
     <spirit:bitWidth>8</spirit:bitWidth>
     <spirit:access>read-write</spirit:access>
    </spirit:field>
    <spirit:field>
     <spirit:name>port1</spirit:name>
     <spirit:description>Number of certain packet type seen</spirit:description>
     <spirit:bitOffset>16</spirit:bitOffset>
     <spirit:bitWidth>8</spirit:bitWidth>
     <spirit:access>read-write</spirit:access>
    </spirit:field>
    <spirit:field>
     <spirit:name>port0</spirit:name>
     <spirit:description>Number of certain packet type seen</spirit:description>
     <spirit:bitOffset>24</spirit:bitOffset>
     <spirit:bitWidth>8</spirit:bitWidth>
     <spirit:access>read-write</spirit:access>
    </spirit:field>
   </spirit:register>
   <spirit:register>
    <spirit:name>fifo_port_0_head</spirit:name>
    <spirit:addressOffset>0x100</spirit:addressOffset>
    <spirit:size>32</spirit:size>
    <spirit:volatile>true</spirit:volatile>
    <spirit:access>read-write</spirit:access>
    <spirit:field>
     <spirit:name>data</spirit:name>
     <spirit:bitOffset>0</spirit:bitOffset>
     <spirit:bitWidth>32</spirit:bitWidth>
     <spirit:access>read-write</spirit:access>
    </spirit:field>
   </spirit:register>
   <spirit:register>
    <spirit:name>fifo_port_0_tail</spirit:name>
    <spirit:addressOffset>0x104</spirit:addressOffset>
    <spirit:size>32</spirit:size>
    <spirit:volatile>true</spirit:volatile>
    <spirit:access>read-write</spirit:access>
    <spirit:field>
     <spirit:name>data</spirit:name>
     <spirit:bitOffset>0</spirit:bitOffset>
     <spirit:bitWidth>32</spirit:bitWidth>
     <spirit:access>read-write</spirit:access>
    </spirit:field>
   </spirit:register>
   <spirit:register>
    <spirit:name>fifo_port_0_status</spirit:name>
    <spirit:addressOffset>0x108</spirit:addressOffset>
    <spirit:size>32</spirit:size>
    <spirit:volatile>true</spirit:volatile>
    <spirit:access>read-write</spirit:access>
    <spirit:reset>
     <spirit:value>0x12</spirit:value>
     <spirit:mask>0xffffffff</spirit:mask>
    </spirit:reset>
    <spirit:field>
     <spirit:name>full</spirit:name>
     <spirit:bitOffset>0</spirit:bitOffset>
     <spirit:bitWidth>1</spirit:bitWidth>
     <spirit:access>read-write</spirit:access>
    </spirit:field>
    <spirit:field>
     <spirit:name>empty</spirit:name>
     <spirit:bitOffset>1</spirit:bitOffset>
     <spirit:bitWidth>1</spirit:bitWidth>
     <spirit:access>read-write</spirit:access>
    </spirit:field>
    <spirit:field>
     <spirit:name>almost_empty</spirit:name>
     <spirit:bitOffset>4</spirit:bitOffset>
     <spirit:bitWidth>1</spirit:bitWidth>
     <spirit:access>read-write</spirit:access>
    </spirit:field>
    <spirit:field>
     <spirit:name>almost_full</spirit:name>
     <spirit:bitOffset>5</spirit:bitOffset>
     <spirit:bitWidth>1</spirit:bitWidth>
     <spirit:access>read-write</spirit:access>
    </spirit:field>
   </spirit:register>
   <spirit:register>
    <spirit:name>fifo_port_1_head</spirit:name>
    <spirit:addressOffset>0x110</spirit:addressOffset>
    <spirit:size>32</spirit:size>
    <spirit:volatile>true</spirit:volatile>
    <spirit:access>read-write</spirit:access>
    <spirit:field>
     <spirit:name>data</spirit:name>
     <spirit:bitOffset>0</spirit:bitOffset>
     <spirit:bitWidth>32</spirit:bitWidth>
     <spirit:access>read-write</spirit:access>
    </spirit:field>
   </spirit:register>
   <spirit:register>
    <spirit:name>fifo_port_1_tail</spirit:name>
    <spirit:addressOffset>0x114</spirit:addressOffset>
    <spirit:size>32</spirit:size>
    <spirit:volatile>true</spirit:volatile>
    <spirit:access>read-write</spirit:access>
    <spirit:field>
     <spirit:name>data</spirit:name>
     <spirit:bitOffset>0</spirit:bitOffset>
     <spirit:bitWidth>32</spirit:bitWidth>
     <spirit:access>read-write</spirit:access>
    </spirit:field>
   </spirit:register>
   <spirit:register>
    <spirit:name>fifo_port_1_status</spirit:name>
    <spirit:addressOffset>0x118</spirit:addressOffset>
    <spirit:size>32</spirit:size>
    <spirit:volatile>true</spirit:volatile>
    <spirit:access>read-write</spirit:access>
    <spirit:reset>
     <spirit:value>0x12</spirit:value>
     <spirit:mask>0xffffffff</spirit:mask>
    </spirit:reset>
    <spirit:field>
     <spirit:name>full</spirit:name>
     <spirit:bitOffset>0</spirit:bitOffset>
     <spirit:bitWidth>1</spirit:bitWidth>
     <spirit:access>read-write</spirit:access>
    </spirit:field>
    <spirit:field>
     <spirit:name>empty</spirit:name>
     <spirit:bitOffset>1</spirit:bitOffset>
     <spirit:bitWidth>1</spirit:bitWidth>
     <spirit:access>read-write</spirit:access>
    </spirit:field>
    <spirit:field>
     <spirit:name>almost_empty</spirit:name>
     <spirit:bitOffset>4</spirit:bitOffset>
     <spirit:bitWidth>1</spirit:bitWidth>
     <spirit:access>read-write</spirit:access>
    </spirit:field>
    <spirit:field>
     <spirit:name>almost_full</spirit:name>
     <spirit:bitOffset>5</spirit:bitOffset>
     <spirit:bitWidth>1</spirit:bitWidth>
     <spirit:access>read-write</spirit:access>
    </spirit:field>
   </spirit:register>
   <spirit:register>
    <spirit:name>fifo_port_2_head</spirit:name>
    <spirit:addressOffset>0x120</spirit:addressOffset>
    <spirit:size>32</spirit:size>
    <spirit:volatile>true</spirit:volatile>
    <spirit:access>read-write</spirit:access>
    <spirit:field>
     <spirit:name>data</spirit:name>
     <spirit:bitOffset>0</spirit:bitOffset>
     <spirit:bitWidth>32</spirit:bitWidth>
     <spirit:access>read-write</spirit:access>
    </spirit:field>
   </spirit:register>
   <spirit:register>
    <spirit:name>fifo_port_2_tail</spirit:name>
    <spirit:addressOffset>0x124</spirit:addressOffset>
    <spirit:size>32</spirit:size>
    <spirit:volatile>true</spirit:volatile>
    <spirit:access>read-write</spirit:access>
    <spirit:field>
     <spirit:name>data</spirit:name>
     <spirit:bitOffset>0</spirit:bitOffset>
     <spirit:bitWidth>32</spirit:bitWidth>
     <spirit:access>read-write</spirit:access>
    </spirit:field>
   </spirit:register>
   <spirit:register>
    <spirit:name>fifo_port_2_status</spirit:name>
    <spirit:addressOffset>0x128</spirit:addressOffset>
    <spirit:size>32</spirit:size>
    <spirit:volatile>true</spirit:volatile>
    <spirit:access>read-write</spirit:access>
    <spirit:reset>
     <spirit:value>0x12</spirit:value>
     <spirit:mask>0xffffffff</spirit:mask>
    </spirit:reset>
    <spirit:field>
     <spirit:name>full</spirit:name>
     <spirit:bitOffset>0</spirit:bitOffset>
     <spirit:bitWidth>1</spirit:bitWidth>
     <spirit:access>read-write</spirit:access>
    </spirit:field>
    <spirit:field>
     <spirit:name>empty</spirit:name>
     <spirit:bitOffset>1</spirit:bitOffset>
     <spirit:bitWidth>1</spirit:bitWidth>
     <spirit:access>read-write</spirit:access>
    </spirit:field>
    <spirit:field>
     <spirit:name>almost_empty</spirit:name>
     <spirit:bitOffset>4</spirit:bitOffset>
     <spirit:bitWidth>1</spirit:bitWidth>
     <spirit:access>read-write</spirit:access>
    </spirit:field>
    <spirit:field>
     <spirit:name>almost_full</spirit:name>
     <spirit:bitOffset>5</spirit:bitOffset>
     <spirit:bitWidth>1</spirit:bitWidth>
     <spirit:access>read-write</spirit:access>
    </spirit:field>
   </spirit:register>
   <spirit:register>
    <spirit:name>fifo_port_3_head</spirit:name>
    <spirit:addressOffset>0x130</spirit:addressOffset>
    <spirit:size>32</spirit:size>
    <spirit:volatile>true</spirit:volatile>
    <spirit:access>read-write</spirit:access>
    <spirit:field>
     <spirit:name>data</spirit:name>
     <spirit:bitOffset>0</spirit:bitOffset>
     <spirit:bitWidth>32</spirit:bitWidth>
     <spirit:access>read-write</spirit:access>
    </spirit:field>
   </spirit:register>
   <spirit:register>
    <spirit:name>fifo_port_3_tail</spirit:name>
    <spirit:addressOffset>0x134</spirit:addressOffset>
    <spirit:size>32</spirit:size>
    <spirit:volatile>true</spirit:volatile>
    <spirit:access>read-write</spirit:access>
    <spirit:field>
     <spirit:name>data</spirit:name>
     <spirit:bitOffset>0</spirit:bitOffset>
     <spirit:bitWidth>32</spirit:bitWidth>
     <spirit:access>read-write</spirit:access>
    </spirit:field>
   </spirit:register>
   <spirit:register>
    <spirit:name>fifo_port_3_status</spirit:name>
    <spirit:addressOffset>0x138</spirit:addressOffset>
    <spirit:size>32</spirit:size>
    <spirit:volatile>true</spirit:volatile>
    <spirit:access>read-write</spirit:access>
    <spirit:reset>
     <spirit:value>0x12</spirit:value>
     <spirit:mask>0xffffffff</spirit:mask>
    </spirit:reset>
    <spirit:field>
     <spirit:name>full</spirit:name>
     <spirit:bitOffset>0</spirit:bitOffset>
     <spirit:bitWidth>1</spirit:bitWidth>
     <spirit:access>read-write</spirit:access>
    </spirit:field>
    <spirit:field>
     <spirit:name>empty</spirit:name>
     <spirit:bitOffset>1</spirit:bitOffset>
     <spirit:bitWidth>1</spirit:bitWidth>
     <spirit:access>read-write</spirit:access>
    </spirit:field>
    <spirit:field>
     <spirit:name>almost_empty</spirit:name>
     <spirit:bitOffset>4</spirit:bitOffset>
     <spirit:bitWidth>1</spirit:bitWidth>
     <spirit:access>read-write</spirit:access>
    </spirit:field>
    <spirit:field>
     <spirit:name>almost_full</spirit:name>
     <spirit:bitOffset>5</spirit:bitOffset>
     <spirit:bitWidth>1</spirit:bitWidth>
     <spirit:access>read-write</spirit:access>
    </spirit:field>
   </spirit:register>
   <spirit:register>
    <spirit:name>fifo_port_4_head</spirit:name>
    <spirit:addressOffset>0x140</spirit:addressOffset>
    <spirit:size>32</spirit:size>
    <spirit:volatile>true</spirit:volatile>
    <spirit:access>read-write</spirit:access>
    <spirit:field>
     <spirit:name>data</spirit:name>
     <spirit:bitOffset>0</spirit:bitOffset>
     <spirit:bitWidth>32</spirit:bitWidth>
     <spirit:access>read-write</spirit:access>
    </spirit:field>
   </spirit:register>
   <spirit:register>
    <spirit:name>fifo_port_4_tail</spirit:name>
    <spirit:addressOffset>0x144</spirit:addressOffset>
    <spirit:size>32</spirit:size>
    <spirit:volatile>true</spirit:volatile>
    <spirit:access>read-write</spirit:access>
    <spirit:field>
     <spirit:name>data</spirit:name>
     <spirit:bitOffset>0</spirit:bitOffset>
     <spirit:bitWidth>32</spirit:bitWidth>
     <spirit:access>read-write</spirit:access>
    </spirit:field>
   </spirit:register>
   <spirit:register>
    <spirit:name>fifo_port_4_status</spirit:name>
    <spirit:addressOffset>0x148</spirit:addressOffset>
    <spirit:size>32</spirit:size>
    <spirit:volatile>true</spirit:volatile>
    <spirit:access>read-write</spirit:access>
    <spirit:reset>
     <spirit:value>0x12</spirit:value>
     <spirit:mask>0xffffffff</spirit:mask>
    </spirit:reset>
    <spirit:field>
     <spirit:name>full</spirit:name>
     <spirit:bitOffset>0</spirit:bitOffset>
     <spirit:bitWidth>1</spirit:bitWidth>
     <spirit:access>read-write</spirit:access>
    </spirit:field>
    <spirit:field>
     <spirit:name>empty</spirit:name>
     <spirit:bitOffset>1</spirit:bitOffset>
     <spirit:bitWidth>1</spirit:bitWidth>
     <spirit:access>read-write</spirit:access>
    </spirit:field>
    <spirit:field>
     <spirit:name>almost_empty</spirit:name>
     <spirit:bitOffset>4</spirit:bitOffset>
     <spirit:bitWidth>1</spirit:bitWidth>
     <spirit:access>read-write</spirit:access>
    </spirit:field>
    <spirit:field>
     <spirit:name>almost_full</spirit:name>
     <spirit:bitOffset>5</spirit:bitOffset>
     <spirit:bitWidth>1</spirit:bitWidth>
     <spirit:access>read-write</spirit:access>
    </spirit:field>
   </spirit:register>
   <spirit:register>
    <spirit:name>fifo_port_5_head</spirit:name>
    <spirit:addressOffset>0x150</spirit:addressOffset>
    <spirit:size>32</spirit:size>
    <spirit:volatile>true</spirit:volatile>
    <spirit:access>read-write</spirit:access>
    <spirit:field>
     <spirit:name>data</spirit:name>
     <spirit:bitOffset>0</spirit:bitOffset>
     <spirit:bitWidth>32</spirit:bitWidth>
     <spirit:access>read-write</spirit:access>
    </spirit:field>
   </spirit:register>
   <spirit:register>
    <spirit:name>fifo_port_5_tail</spirit:name>
    <spirit:addressOffset>0x154</spirit:addressOffset>
    <spirit:size>32</spirit:size>
    <spirit:volatile>true</spirit:volatile>
    <spirit:access>read-write</spirit:access>
    <spirit:field>
     <spirit:name>data</spirit:name>
     <spirit:bitOffset>0</spirit:bitOffset>
     <spirit:bitWidth>32</spirit:bitWidth>
     <spirit:access>read-write</spirit:access>
    </spirit:field>
   </spirit:register>
   <spirit:register>
    <spirit:name>fifo_port_5_status</spirit:name>
    <spirit:addressOffset>0x158</spirit:addressOffset>
    <spirit:size>32</spirit:size>
    <spirit:volatile>true</spirit:volatile>
    <spirit:access>read-write</spirit:access>
    <spirit:reset>
     <spirit:value>0x12</spirit:value>
     <spirit:mask>0xffffffff</spirit:mask>
    </spirit:reset>
    <spirit:field>
     <spirit:name>full</spirit:name>
     <spirit:bitOffset>0</spirit:bitOffset>
     <spirit:bitWidth>1</spirit:bitWidth>
     <spirit:access>read-write</spirit:access>
    </spirit:field>
    <spirit:field>
     <spirit:name>empty</spirit:name>
     <spirit:bitOffset>1</spirit:bitOffset>
     <spirit:bitWidth>1</spirit:bitWidth>
     <spirit:access>read-write</spirit:access>
    </spirit:field>
    <spirit:field>
     <spirit:name>almost_empty</spirit:name>
     <spirit:bitOffset>4</spirit:bitOffset>
     <spirit:bitWidth>1</spirit:bitWidth>
     <spirit:access>read-write</spirit:access>
    </spirit:field>
    <spirit:field>
     <spirit:name>almost_full</spirit:name>
     <spirit:bitOffset>5</spirit:bitOffset>
     <spirit:bitWidth>1</spirit:bitWidth>
     <spirit:access>read-write</spirit:access>
    </spirit:field>
   </spirit:register>
   <spirit:register>
    <spirit:name>fifo_port_6_head</spirit:name>
    <spirit:addressOffset>0x160</spirit:addressOffset>
    <spirit:size>32</spirit:size>
    <spirit:volatile>true</spirit:volatile>
    <spirit:access>read-write</spirit:access>
    <spirit:field>
     <spirit:name>data</spirit:name>
     <spirit:bitOffset>0</spirit:bitOffset>
     <spirit:bitWidth>32</spirit:bitWidth>
     <spirit:access>read-write</spirit:access>
    </spirit:field>
   </spirit:register>
   <spirit:register>
    <spirit:name>fifo_port_6_tail</spirit:name>
    <spirit:addressOffset>0x164</spirit:addressOffset>
    <spirit:size>32</spirit:size>
    <spirit:volatile>true</spirit:volatile>
    <spirit:access>read-write</spirit:access>
    <spirit:field>
     <spirit:name>data</spirit:name>
     <spirit:bitOffset>0</spirit:bitOffset>
     <spirit:bitWidth>32</spirit:bitWidth>
     <spirit:access>read-write</spirit:access>
    </spirit:field>
   </spirit:register>
   <spirit:register>
    <spirit:name>fifo_port_6_status</spirit:name>
    <spirit:addressOffset>0x168</spirit:addressOffset>
    <spirit:size>32</spirit:size>
    <spirit:volatile>true</spirit:volatile>
    <spirit:access>read-write</spirit:access>
    <spirit:reset>
     <spirit:value>0x12</spirit:value>
     <spirit:mask>0xffffffff</spirit:mask>
    </spirit:reset>
    <spirit:field>
     <spirit:name>full</spirit:name>
     <spirit:bitOffset>0</spirit:bitOffset>
     <spirit:bitWidth>1</spirit:bitWidth>
     <spirit:access>read-write</spirit:access>
    </spirit:field>
    <spirit:field>
     <spirit:name>empty</spirit:name>
     <spirit:bitOffset>1</spirit:bitOffset>
     <spirit:bitWidth>1</spirit:bitWidth>
     <spirit:access>read-write</spirit:access>
    </spirit:field>
    <spirit:field>
     <spirit:name>almost_empty</spirit:name>
     <spirit:bitOffset>4</spirit:bitOffset>
     <spirit:bitWidth>1</spirit:bitWidth>
     <spirit:access>read-write</spirit:access>
    </spirit:field>
    <spirit:field>
     <spirit:name>almost_full</spirit:name>
     <spirit:bitOffset>5</spirit:bitOffset>
     <spirit:bitWidth>1</spirit:bitWidth>
     <spirit:access>read-write</spirit:access>
    </spirit:field>
   </spirit:register>
   <spirit:register>
    <spirit:name>fifo_port_7_head</spirit:name>
    <spirit:addressOffset>0x170</spirit:addressOffset>
    <spirit:size>32</spirit:size>
    <spirit:volatile>true</spirit:volatile>
    <spirit:access>read-write</spirit:access>
    <spirit:field>
     <spirit:name>data</spirit:name>
     <spirit:bitOffset>0</spirit:bitOffset>
     <spirit:bitWidth>32</spirit:bitWidth>
     <spirit:access>read-write</spirit:access>
    </spirit:field>
   </spirit:register>
   <spirit:register>
    <spirit:name>fifo_port_7_tail</spirit:name>
    <spirit:addressOffset>0x174</spirit:addressOffset>
    <spirit:size>32</spirit:size>
    <spirit:volatile>true</spirit:volatile>
    <spirit:access>read-write</spirit:access>
    <spirit:field>
     <spirit:name>data</spirit:name>
     <spirit:bitOffset>0</spirit:bitOffset>
     <spirit:bitWidth>32</spirit:bitWidth>
     <spirit:access>read-write</spirit:access>
    </spirit:field>
   </spirit:register>
   <spirit:register>
    <spirit:name>fifo_port_7_status</spirit:name>
    <spirit:addressOffset>0x178</spirit:addressOffset>
    <spirit:size>32</spirit:size>
    <spirit:volatile>true</spirit:volatile>
    <spirit:access>read-write</spirit:access>
    <spirit:reset>
     <spirit:value>0x12</spirit:value>
     <spirit:mask>0xffffffff</spirit:mask>
    </spirit:reset>
    <spirit:field>
     <spirit:name>full</spirit:name>
     <spirit:bitOffset>0</spirit:bitOffset>
     <spirit:bitWidth>1</spirit:bitWidth>
     <spirit:access>read-write</spirit:access>
    </spirit:field>
    <spirit:field>
     <spirit:name>empty</spirit:name>
     <spirit:bitOffset>1</spirit:bitOffset>
     <spirit:bitWidth>1</spirit:bitWidth>
     <spirit:access>read-write</spirit:access>
    </spirit:field>
    <spirit:field>
     <spirit:name>almost_empty</spirit:name>
     <spirit:bitOffset>4</spirit:bitOffset>
     <spirit:bitWidth>1</spirit:bitWidth>
     <spirit:access>read-write</spirit:access>
    </spirit:field>
    <spirit:field>
     <spirit:name>almost_full</spirit:name>
     <spirit:bitOffset>5</spirit:bitOffset>
     <spirit:bitWidth>1</spirit:bitWidth>
     <spirit:access>read-write</spirit:access>
    </spirit:field>
   </spirit:register>
   <spirit:register>
    <spirit:name>vc_pkt_count_0</spirit:name>
    <spirit:addressOffset>0x1000</spirit:addressOffset>
    <spirit:size>32</spirit:size>
    <spirit:volatile>true</spirit:volatile>
    <spirit:access>read-write</spirit:access>
    <spirit:reset>
     <spirit:value>0x80000000</spirit:value>
     <spirit:mask>0xffffffff</spirit:mask>
    </spirit:reset>
    <spirit:field>
     <spirit:name>vc_count</spirit:name>
     <spirit:description>Number of certain packet type seen</spirit:description>
     <spirit:bitOffset>0</spirit:bitOffset>
     <spirit:bitWidth>31</spirit:bitWidth>
     <spirit:access>read-write</spirit:access>
    </spirit:field>
    <spirit:field>
     <spirit:name>active</spirit:name>
     <spirit:description>VC is Active</spirit:description>
     <spirit:bitOffset>31</spirit:bitOffset>
     <spirit:bitWidth>1</spirit:bitWidth>
     <spirit:access>read-write</spirit:access>
    </spirit:field>
   </spirit:register>
   <spirit:register>
    <spirit:name>vc_pkt_count_1</spirit:name>
    <spirit:addressOffset>0x1010</spirit:addressOffset>
    <spirit:size>32</spirit:size>
    <spirit:volatile>true</spirit:volatile>
    <spirit:access>read-write</spirit:access>
    <spirit:reset>
     <spirit:value>0x80000000</spirit:value>
     <spirit:mask>0xffffffff</spirit:mask>
    </spirit:reset>
    <spirit:field>
     <spirit:name>vc_count</spirit:name>
     <spirit:description>Number of certain packet type seen</spirit:description>
     <spirit:bitOffset>0</spirit:bitOffset>
     <spirit:bitWidth>31</spirit:bitWidth>
     <spirit:access>read-write</spirit:access>
    </spirit:field>
    <spirit:field>
     <spirit:name>active</spirit:name>
     <spirit:description>VC is Active</spirit:description>
     <spirit:bitOffset>31</spirit:bitOffset>
     <spirit:bitWidth>1</spirit:bitWidth>
     <spirit:access>read-write</spirit:access>
    </spirit:field>
   </spirit:register>
   <spirit:register>
    <spirit:name>vc_pkt_count_2</spirit:name>
    <spirit:addressOffset>0x1020</spirit:addressOffset>
    <spirit:size>32</spirit:size>
    <spirit:volatile>true</spirit:volatile>
    <spirit:access>read-write</spirit:access>
    <spirit:reset>
     <spirit:value>0x80000000</spirit:value>
     <spirit:mask>0xffffffff</spirit:mask>
    </spirit:reset>
    <spirit:field>
     <spirit:name>vc_count</spirit:name>
     <spirit:description>Number of certain packet type seen</spirit:description>
     <spirit:bitOffset>0</spirit:bitOffset>
     <spirit:bitWidth>31</spirit:bitWidth>
     <spirit:access>read-write</spirit:access>
    </spirit:field>
    <spirit:field>
     <spirit:name>active</spirit:name>
     <spirit:description>VC is Active</spirit:description>
     <spirit:bitOffset>31</spirit:bitOffset>
     <spirit:bitWidth>1</spirit:bitWidth>
     <spirit:access>read-write</spirit:access>
    </spirit:field>
   </spirit:register>
   <spirit:register>
    <spirit:name>vc_pkt_count_3</spirit:name>
    <spirit:addressOffset>0x1030</spirit:addressOffset>
    <spirit:size>32</spirit:size>
    <spirit:volatile>true</spirit:volatile>
    <spirit:access>read-write</spirit:access>
    <spirit:reset>
     <spirit:value>0x80000000</spirit:value>
     <spirit:mask>0xffffffff</spirit:mask>
    </spirit:reset>
    <spirit:field>
     <spirit:name>vc_count</spirit:name>
     <spirit:description>Number of certain packet type seen</spirit:description>
     <spirit:bitOffset>0</spirit:bitOffset>
     <spirit:bitWidth>31</spirit:bitWidth>
     <spirit:access>read-write</spirit:access>
    </spirit:field>
    <spirit:field>
     <spirit:name>active</spirit:name>
     <spirit:description>VC is Active</spirit:description>
     <spirit:bitOffset>31</spirit:bitOffset>
     <spirit:bitWidth>1</spirit:bitWidth>
     <spirit:access>read-write</spirit:access>
    </spirit:field>
   </spirit:register>
   <spirit:register>
    <spirit:name>vc_pkt_count_4</spirit:name>
    <spirit:addressOffset>0x1040</spirit:addressOffset>
    <spirit:size>32</spirit:size>
    <spirit:volatile>true</spirit:volatile>
    <spirit:access>read-write</spirit:access>
    <spirit:reset>
     <spirit:value>0x80000000</spirit:value>
     <spirit:mask>0xffffffff</spirit:mask>
    </spirit:reset>
    <spirit:field>
     <spirit:name>vc_count</spirit:name>
     <spirit:description>Number of certain packet type seen</spirit:description>
     <spirit:bitOffset>0</spirit:bitOffset>
     <spirit:bitWidth>31</spirit:bitWidth>
     <spirit:access>read-write</spirit:access>
    </spirit:field>
    <spirit:field>
     <spirit:name>active</spirit:name>
     <spirit:description>VC is Active</spirit:description>
     <spirit:bitOffset>31</spirit:bitOffset>
     <spirit:bitWidth>1</spirit:bitWidth>
     <spirit:access>read-write</spirit:access>
    </spirit:field>
   </spirit:register>
   <spirit:register>
    <spirit:name>vc_pkt_count_5</spirit:name>
    <spirit:addressOffset>0x1050</spirit:addressOffset>
    <spirit:size>32</spirit:size>
    <spirit:volatile>true</spirit:volatile>
    <spirit:access>read-write</spirit:access>
    <spirit:reset>
     <spirit:value>0x80000000</spirit:value>
     <spirit:mask>0xffffffff</spirit:mask>
    </spirit:reset>
    <spirit:field>
     <spirit:name>vc_count</spirit:name>
     <spirit:description>Number of certain packet type seen</spirit:description>
     <spirit:bitOffset>0</spirit:bitOffset>
     <spirit:bitWidth>31</spirit:bitWidth>
     <spirit:access>read-write</spirit:access>
    </spirit:field>
    <spirit:field>
     <spirit:name>active</spirit:name>
     <spirit:description>VC is Active</spirit:description>
     <spirit:bitOffset>31</spirit:bitOffset>
     <spirit:bitWidth>1</spirit:bitWidth>
     <spirit:access>read-write</spirit:access>
    </spirit:field>
   </spirit:register>
   <spirit:register>
    <spirit:name>vc_pkt_count_6</spirit:name>
    <spirit:addressOffset>0x1060</spirit:addressOffset>
    <spirit:size>32</spirit:size>
    <spirit:volatile>true</spirit:volatile>
    <spirit:access>read-write</spirit:access>
    <spirit:reset>
     <spirit:value>0x80000000</spirit:value>
     <spirit:mask>0xffffffff</spirit:mask>
    </spirit:reset>
    <spirit:field>
     <spirit:name>vc_count</spirit:name>
     <spirit:description>Number of certain packet type seen</spirit:description>
     <spirit:bitOffset>0</spirit:bitOffset>
     <spirit:bitWidth>31</spirit:bitWidth>
     <spirit:access>read-write</spirit:access>
    </spirit:field>
    <spirit:field>
     <spirit:name>active</spirit:name>
     <spirit:description>VC is Active</spirit:description>
     <spirit:bitOffset>31</spirit:bitOffset>
     <spirit:bitWidth>1</spirit:bitWidth>
     <spirit:access>read-write</spirit:access>
    </spirit:field>
   </spirit:register>
   <spirit:register>
    <spirit:name>vc_pkt_count_7</spirit:name>
    <spirit:addressOffset>0x1070</spirit:addressOffset>
    <spirit:size>32</spirit:size>
    <spirit:volatile>true</spirit:volatile>
    <spirit:access>read-write</spirit:access>
    <spirit:reset>
     <spirit:value>0x80000000</spirit:value>
     <spirit:mask>0xffffffff</spirit:mask>
    </spirit:reset>
    <spirit:field>
     <spirit:name>vc_count</spirit:name>
     <spirit:description>Number of certain packet type seen</spirit:description>
     <spirit:bitOffset>0</spirit:bitOffset>
     <spirit:bitWidth>31</spirit:bitWidth>
     <spirit:access>read-write</spirit:access>
    </spirit:field>
    <spirit:field>
     <spirit:name>active</spirit:name>
     <spirit:description>VC is Active</spirit:description>
     <spirit:bitOffset>31</spirit:bitOffset>
     <spirit:bitWidth>1</spirit:bitWidth>
     <spirit:access>read-write</spirit:access>
    </spirit:field>
   </spirit:register>
   <spirit:register>
    <spirit:name>vc_pkt_count_8</spirit:name>
    <spirit:addressOffset>0x1080</spirit:addressOffset>
    <spirit:size>32</spirit:size>
    <spirit:volatile>true</spirit:volatile>
    <spirit:access>read-write</spirit:access>
    <spirit:reset>
     <spirit:value>0x80000000</spirit:value>
     <spirit:mask>0xffffffff</spirit:mask>
    </spirit:reset>
    <spirit:field>
     <spirit:name>vc_count</spirit:name>
     <spirit:description>Number of certain packet type seen</spirit:description>
     <spirit:bitOffset>0</spirit:bitOffset>
     <spirit:bitWidth>31</spirit:bitWidth>
     <spirit:access>read-write</spirit:access>
    </spirit:field>
    <spirit:field>
     <spirit:name>active</spirit:name>
     <spirit:description>VC is Active</spirit:description>
     <spirit:bitOffset>31</spirit:bitOffset>
     <spirit:bitWidth>1</spirit:bitWidth>
     <spirit:access>read-write</spirit:access>
    </spirit:field>
   </spirit:register>
   <spirit:register>
    <spirit:name>vc_pkt_count_9</spirit:name>
    <spirit:addressOffset>0x1090</spirit:addressOffset>
    <spirit:size>32</spirit:size>
    <spirit:volatile>true</spirit:volatile>
    <spirit:access>read-write</spirit:access>
    <spirit:reset>
     <spirit:value>0x80000000</spirit:value>
     <spirit:mask>0xffffffff</spirit:mask>
    </spirit:reset>
    <spirit:field>
     <spirit:name>vc_count</spirit:name>
     <spirit:description>Number of certain packet type seen</spirit:description>
     <spirit:bitOffset>0</spirit:bitOffset>
     <spirit:bitWidth>31</spirit:bitWidth>
     <spirit:access>read-write</spirit:access>
    </spirit:field>
    <spirit:field>
     <spirit:name>active</spirit:name>
     <spirit:description>VC is Active</spirit:description>
     <spirit:bitOffset>31</spirit:bitOffset>
     <spirit:bitWidth>1</spirit:bitWidth>
     <spirit:access>read-write</spirit:access>
    </spirit:field>
   </spirit:register>
   <spirit:register>
    <spirit:name>vc_pkt_count_10</spirit:name>
    <spirit:description>Helpful description</spirit:description>
    <spirit:addressOffset>0x10a0</spirit:addressOffset>
    <spirit:size>32</spirit:size>
    <spirit:volatile>true</spirit:volatile>
    <spirit:access>read-write</spirit:access>
    <spirit:reset>
     <spirit:value>0x80000000</spirit:value>
     <spirit:mask>0xffffffff</spirit:mask>
    </spirit:reset>
    <spirit:field>
     <spirit:name>vc_count</spirit:name>
     <spirit:description>Number of certain packet type seen</spirit:description>
     <spirit:bitOffset>0</spirit:bitOffset>
     <spirit:bitWidth>31</spirit:bitWidth>
     <spirit:access>read-write</spirit:access>
    </spirit:field>
    <spirit:field>
     <spirit:name>active</spirit:name>
     <spirit:description>VC is Active</spirit:description>
     <spirit:bitOffset>31</spirit:bitOffset>
     <spirit:bitWidth>1</spirit:bitWidth>
     <spirit:access>read-write</spirit:access>
    </spirit:field>
   </spirit:register>
  </spirit:addressBlock>
 </spirit:memoryMap>
</spirit:memoryMaps>
	<spirit:model>
		<spirit:views>
			<spirit:view>
				<spirit:name>flat</spirit:name>
				<spirit:envIdentifier>::</spirit:envIdentifier>
				<spirit:vendorExtensions>
					<kactus2:componentInstantiation>
						<spirit:name>flat</spirit:name>
					</kactus2:componentInstantiation>
				</spirit:vendorExtensions>
			</spirit:view>
		</spirit:views>
	</spirit:model>
	<spirit:fileSets>
		<spirit:fileSet>
			<spirit:name>rtl_files</spirit:name>
			<spirit:file>
				<spirit:name>rtl/verilog/example_top.v</spirit:name>
				<spirit:fileType>verilogSource</spirit:fileType>
				<spirit:isIncludeFile spirit:externalDeclarations="false">false</spirit:isIncludeFile>
			</spirit:file>
			<spirit:file>
				<spirit:name>rtl/verilog/example_core.v</spirit:name>
				<spirit:fileType>verilogSource</spirit:fileType>
				<spirit:isIncludeFile spirit:externalDeclarations="false">false</spirit:isIncludeFile>
			</spirit:file>
		</spirit:fileSet>
		<spirit:fileSet>
			<spirit:name>tb_files</spirit:name>
			<spirit:file>
				<spirit:name>bench/example_tb.v</spirit:name>
				<spirit:fileType>verilogSource</spirit:fileType>
				<spirit:isIncludeFile spirit:externalDeclarations="false">false</spirit:isIncludeFile>
			</spirit:file>
		</spirit:fileSet>
	</spirit:fileSets>
	<spirit:description>This is the description field of the example component</spirit:description>
	<spirit:vendorExtensions>
		<kactus2:extensions>
			<kactus2:kts_attributes>
				<kactus2:kts_productHier>Flat</kactus2:kts_productHier>
				<kactus2:kts_implementation>HW</kactus2:kts_implementation>
				<kactus2:kts_firmness>Mutable</kactus2:kts_firmness>
			</kactus2:kts_attributes>
			<kactus2:author>olof</kactus2:author>
		</kactus2:extensions>
		<kactus2:version>2,8,49,0</kactus2:version>
	</spirit:vendorExtensions>
</spirit:component>
